vectorgov/cli/__init__.py
vectorgov/cli/main.py
vectorgov/cli/commands/__init__.py
vectorgov/cli/commands/ask.py
vectorgov/cli/commands/auth.py
vectorgov/cli/commands/config.py
vectorgov/cli/commands/docs.py
vectorgov/cli/commands/feedback.py
vectorgov/cli/commands/search.py
vectorgov/cli/commands/tokens.py
vectorgov/cli/utils/__init__.py
vectorgov/cli/utils/config.py
vectorgov/cli/utils/output.py
vectorgov_cli-0.1.4.dist-info/METADATA
vectorgov_cli-0.1.4.dist-info/WHEEL
vectorgov_cli-0.1.4.dist-info/entry_points.txt
vectorgov_cli-0.1.4.dist-info/RECORD
