Metadata-Version: 2.4
Name: vectorgov-cli
Version: 0.1.4
Summary: CLI para a API VectorGov - Busca semântica em legislação brasileira
Project-URL: Homepage, https://vectorgov.io
Project-URL: Documentation, https://vectorgov.io/documentacao
Project-URL: Repository, https://github.com/euteajudo/vectorgov-cli
Project-URL: Issues, https://github.com/euteajudo/vectorgov-cli/issues
Author-email: VectorGov <contato@vectorgov.io>
License-Expression: MIT
Keywords: brazil,cli,legal,legislation,licitacao,rag,semantic-search,vectorgov
Classifier: Development Status :: 4 - Beta
Classifier: Environment :: Console
Classifier: Intended Audience :: Developers
Classifier: License :: OSI Approved :: MIT License
Classifier: Operating System :: OS Independent
Classifier: Programming Language :: Python :: 3
Classifier: Programming Language :: Python :: 3.9
Classifier: Programming Language :: Python :: 3.10
Classifier: Programming Language :: Python :: 3.11
Classifier: Programming Language :: Python :: 3.12
Classifier: Topic :: Software Development :: Libraries :: Python Modules
Classifier: Topic :: Text Processing :: Linguistic
Requires-Python: >=3.9
Requires-Dist: pyyaml>=6.0.0
Requires-Dist: rich>=13.0.0
Requires-Dist: typer>=0.9.0
Requires-Dist: vectorgov>=0.13.0
Provides-Extra: all
Requires-Dist: anthropic>=0.18.0; extra == 'all'
Requires-Dist: google-generativeai>=0.3.0; extra == 'all'
Requires-Dist: langchain-core>=0.1.0; extra == 'all'
Requires-Dist: langchain>=0.1.0; extra == 'all'
Requires-Dist: openai>=1.0.0; extra == 'all'
Provides-Extra: anthropic
Requires-Dist: anthropic>=0.18.0; extra == 'anthropic'
Provides-Extra: dev
Requires-Dist: black>=23.0.0; extra == 'dev'
Requires-Dist: isort>=5.12.0; extra == 'dev'
Requires-Dist: mypy>=1.0.0; extra == 'dev'
Requires-Dist: pytest-asyncio>=0.21.0; extra == 'dev'
Requires-Dist: pytest-cov>=4.0.0; extra == 'dev'
Requires-Dist: pytest>=7.0.0; extra == 'dev'
Requires-Dist: ruff>=0.1.0; extra == 'dev'
Provides-Extra: google
Requires-Dist: google-generativeai>=0.3.0; extra == 'google'
Provides-Extra: langchain
Requires-Dist: langchain-core>=0.1.0; extra == 'langchain'
Requires-Dist: langchain>=0.1.0; extra == 'langchain'
Provides-Extra: openai
Requires-Dist: openai>=1.0.0; extra == 'openai'
